sqlalchemy_dm/__init__.py
sqlalchemy_dm/base.py
sqlalchemy_dm/dmPython.py
sqlalchemy_dm/types.py
sqlalchemy_dm_pkg-2.0.4.dist-info/licenses/LICENSE
sqlalchemy_dm_pkg-2.0.4.dist-info/METADATA
sqlalchemy_dm_pkg-2.0.4.dist-info/WHEEL
sqlalchemy_dm_pkg-2.0.4.dist-info/entry_points.txt
sqlalchemy_dm_pkg-2.0.4.dist-info/top_level.txt
sqlalchemy_dm_pkg-2.0.4.dist-info/RECORD
